{
  "period": "month",
  "dateStart": "2026-05-01",
  "dateEnd": "2026-05-31",
  "date": "2026-05-01至2026-05-31",
  "category": "游戏",
  "periodLabel": "月榜",
  "total": 50,
  "list": [
    {
      "rank": 1,
      "accountName": "陈伯(全能王)",
      "category": "游戏",
      "comprehensiveScore": 78.5,
      "followers": "1629.32w",
      "newFans": "298.10w",
      "newLikes": "95.64w",
      "newComments": "143.00w",
      "newShares": "33.08w",
      "profileUrl": "https://www.douyin.com/user/MS4wLjABAAAAe6cnO6wkp9c-onOKNWD2sv-x4e61H4HHbRqNWgyZUD0"
    },
    {
      "rank": 2,
      "accountName": "KPL王者荣耀职业联赛",
      "category": "游戏",
      "comprehensiveScore": 73.9,
      "followers": "473.89w",
      "newFans": "38.08w",
      "newLikes": "793.19w",
      "newComments": "22.54w",
      "newShares": "84.88w",
      "profileUrl": "https://www.douyin.com/user/MS4wLjABAAAAJlcKdauqGCW8o73qnQ57jsxU7T3SQaRAafRQvQzoqfA"
    },
    {
      "rank": 3,
      "accountName": "林树（三角洲行动）",
      "category": "游戏",
      "comprehensiveScore": 73.2,
      "followers": "1162.89w",
      "newFans": "51.92w",
      "newLikes": "735.65w",
      "newComments": "11.92w",
      "newShares": "42.57w",
      "profileUrl": "https://www.douyin.com/user/MS4wLjABAAAAYSOcrkBBqaB3slbNIj7wqaOLcGlJrjx7vl6XhruDUEw"
    },
    {
      "rank": 4,
      "accountName": "Gus",
      "category": "游戏",
      "comprehensiveScore": 72.8,
      "followers": "400.07w",
      "newFans": "22.71w",
      "newLikes": "146.38w",
      "newComments": "7974",
      "newShares": "13.78w",
      "profileUrl": "https://www.douyin.com/user/MS4wLjABAAAAigD3FYb1hZWuz_rrD1V25V2hlpCkO3NtT7GDMJlwvkI"
    },
    {
      "rank": 5,
      "accountName": "昊天（三角洲行动）",
      "category": "游戏",
      "comprehensiveScore": 72,
      "followers": "754.89w",
      "newFans": "62.71w",
      "newLikes": "489.05w",
      "newComments": "14.46w",
      "newShares": "43.78w",
      "profileUrl": "https://www.douyin.com/user/MS4wLjABAAAASForPadPPv9GmWgbyZ_SoYTzqwUGitSJmuq-PtTFfC3MocLMGYYZC1xuvUpiJaSj"
    },
    {
      "rank": 6,
      "accountName": "HangHang",
      "category": "游戏",
      "comprehensiveScore": 71.4,
      "followers": "1027.59w",
      "newFans": "45.68w",
      "newLikes": "649.07w",
      "newComments": "6.81w",
      "newShares": "48.47w",
      "profileUrl": "https://www.douyin.com/user/MS4wLjABAAAAZX-0fCG3Wa8mkZpyvTgB-QA3jTvFWY1TSJagDaemIpA"
    },
    {
      "rank": 7,
      "accountName": "网易第五人格",
      "category": "游戏",
      "comprehensiveScore": 71.3,
      "followers": "684.21w",
      "newFans": "4.96w",
      "newLikes": "617.70w",
      "newComments": "54.13w",
      "newShares": "135.56w",
      "profileUrl": "https://www.douyin.com/user/MS4wLjABAAAAT0MzELnLBWdfhED5ZZvwOdj8Ni0DySts9vVFSdYiT1M"
    },
    {
      "rank": 8,
      "accountName": "小蘑菇秃秃的日常",
      "category": "游戏",
      "comprehensiveScore": 71.2,
      "followers": "125.35w",
      "newFans": "69.78w",
      "newLikes": "422.86w",
      "newComments": "8.89w",
      "newShares": "167.11w",
      "profileUrl": "https://www.douyin.com/user/MS4wLjABAAAA6F9PR2voC0sRQoOXjVJ0n59WJRKJfOxDv8HhhWCnFVA1emKWiBMa8SYSHb9IP7iW"
    },
    {
      "rank": 9,
      "accountName": "ZmjjKK",
      "category": "游戏",
      "comprehensiveScore": 68.2,
      "followers": "225.45w",
      "newFans": "57.43w",
      "newLikes": "436.67w",
      "newComments": "7.63w",
      "newShares": "63.32w",
      "profileUrl": "https://www.douyin.com/user/MS4wLjABAAAAryXUu1em2dWVEvX66dBhRwHVsbGyD1lmPCzZttY6gUA"
    },
    {
      "rank": 10,
      "accountName": "bbFps（三角洲行动）",
      "category": "游戏",
      "comprehensiveScore": 68.1,
      "followers": "311.89w",
      "newFans": "77.65w",
      "newLikes": "305.95w",
      "newComments": "18.63w",
      "newShares": "30.83w",
      "profileUrl": "https://www.douyin.com/user/MS4wLjABAAAAQXrg83g71nOogVJUHyqAXBBEIECalpsbwTjq_ngE5oM"
    },
    {
      "rank": 11,
      "accountName": "等我刷把宗师",
      "category": "游戏",
      "comprehensiveScore": 67.6,
      "followers": "534.29w",
      "newFans": "66.37w",
      "newLikes": "176.41w",
      "newComments": "7.46w",
      "newShares": "53.07w",
      "profileUrl": "https://www.douyin.com/user/MS4wLjABAAAAmuYH81JnFEpHbmXoqS0PRsPWroJiFxYbMw0X1K7lR-k"
    },
    {
      "rank": 12,
      "accountName": "三角洲行动",
      "category": "游戏",
      "comprehensiveScore": 67.2,
      "followers": "845.06w",
      "newFans": "20.73w",
      "newLikes": "222.75w",
      "newComments": "22.06w",
      "newShares": "45.78w",
      "profileUrl": "https://www.douyin.com/user/MS4wLjABAAAAi-Nwh-jlfuUgL9gfCKvlEvSRUfj9ooGqJN7S0FoMIk8"
    },
    {
      "rank": 13,
      "accountName": "王浩宇Whys",
      "category": "游戏",
      "comprehensiveScore": 67.1,
      "followers": "520.72w",
      "newFans": "104.06w",
      "newLikes": "224.58w",
      "newComments": "9.10w",
      "newShares": "23.66w",
      "profileUrl": "https://www.douyin.com/user/MS4wLjABAAAAKIvMlEhOmwIIXsmwhqMw4R9Grm2PLpO8L9PyDM1BzMY"
    },
    {
      "rank": 14,
      "accountName": "煮酒论枭雄",
      "category": "游戏",
      "comprehensiveScore": 65.9,
      "followers": "310.55w",
      "newFans": "8.61w",
      "newLikes": "344.81w",
      "newComments": "20.53w",
      "newShares": "100.90w",
      "profileUrl": "https://www.douyin.com/user/MS4wLjABAAAAsFL91bhVsEDoW39ZsExLDP6vhQ901VeWqx_eANoIMjJM4fKuSnka68tqyBHJs87j"
    },
    {
      "rank": 15,
      "accountName": "洛克王国世界",
      "category": "游戏",
      "comprehensiveScore": 65,
      "followers": "155.58w",
      "newFans": "22.60w",
      "newLikes": "230.80w",
      "newComments": "21.06w",
      "newShares": "77.89w",
      "profileUrl": "https://www.douyin.com/user/MS4wLjABAAAAeQwmvyLYQtnR2038gPlXMtfk6twXv2CqajJG4Q61043M9PTLcwFHuihQanvDdVKN"
    },
    {
      "rank": 16,
      "accountName": "无畏契约",
      "category": "游戏",
      "comprehensiveScore": 64.9,
      "followers": "385.82w",
      "newFans": "6.64w",
      "newLikes": "193.50w",
      "newComments": "23.75w",
      "newShares": "118.99w",
      "profileUrl": "https://www.douyin.com/user/MS4wLjABAAAAd61SOvCplM1lOsnVcBKjGntfjcQ-gyFBN7PdPVOpE6k"
    },
    {
      "rank": 17,
      "accountName": "崩坏星穹铁道",
      "category": "游戏",
      "comprehensiveScore": 63.1,
      "followers": "534.92w",
      "newFans": "10.62w",
      "newLikes": "350.86w",
      "newComments": "6.25w",
      "newShares": "52.27w",
      "profileUrl": "https://www.douyin.com/user/MS4wLjABAAAAsWXxS-KIWEuFJf2oy9E5RwDFzqIElxMsYccLGHCTh-J7z4WhTCehpsQwkv0n_8pl"
    },
    {
      "rank": 18,
      "accountName": "益智乐园",
      "category": "游戏",
      "comprehensiveScore": 61.9,
      "followers": "177.32w",
      "newFans": "92.85w",
      "newLikes": "163.48w",
      "newComments": "34.97w",
      "newShares": "8.38w",
      "profileUrl": "https://www.douyin.com/user/MS4wLjABAAAAYh5cAvIm3rcKqnJCE2xI6wR1goEKkOnutEhAjzKx4b0"
    },
    {
      "rank": 19,
      "accountName": "安澜（三角洲行动）",
      "category": "游戏",
      "comprehensiveScore": 61.3,
      "followers": "431.68w",
      "newFans": "35.11w",
      "newLikes": "345.18w",
      "newComments": "4.03w",
      "newShares": "16.78w",
      "profileUrl": "https://www.douyin.com/user/MS4wLjABAAAAyxKY3uQtojZls91oiUCJgUQAqtecxHskRVshnb90taWJsvMVPyP1-9CGRCOOL470"
    },
    {
      "rank": 20,
      "accountName": "里昂聊游戏",
      "category": "游戏",
      "comprehensiveScore": 61.2,
      "followers": "558.59w",
      "newFans": "15.17w",
      "newLikes": "150.74w",
      "newComments": "3.97w",
      "newShares": "54.80w",
      "profileUrl": "https://www.douyin.com/user/MS4wLjABAAAA0MVlR5kP10FWG04ioBoJ3xQ0HlPneNdoJulfi5rW8vSTqGJb2w2p137mVJ8nT0j_"
    },
    {
      "rank": 21,
      "accountName": "梨涡圆圆的",
      "category": "游戏",
      "comprehensiveScore": 61.1,
      "followers": "204.18w",
      "newFans": "132.22w",
      "newLikes": "238.81w",
      "newComments": "1.91w",
      "newShares": "14.80w",
      "profileUrl": "https://www.douyin.com/user/MS4wLjABAAAAPFz6Uor4YnlUhLZVOxepaBY5c3vTH-iIKmOsutFXyH3XSJ_8uNZd7T1XDQjtVuea"
    },
    {
      "rank": 22,
      "accountName": "小正（又细又快的枪）",
      "category": "游戏",
      "comprehensiveScore": 61,
      "followers": "463.74w",
      "newFans": "43.72w",
      "newLikes": "119.52w",
      "newComments": "2.04w",
      "newShares": "37.51w",
      "profileUrl": "https://www.douyin.com/user/MS4wLjABAAAAOPmUR2taD94_BIIUHf3E9SyyuoKlUf6OkMbPjcSCkug"
    },
    {
      "rank": 23,
      "accountName": "成成大王（三角洲行动）",
      "category": "游戏",
      "comprehensiveScore": 60.5,
      "followers": "250.75w",
      "newFans": "54.35w",
      "newLikes": "308.86w",
      "newComments": "3.43w",
      "newShares": "15.72w",
      "profileUrl": "https://www.douyin.com/user/MS4wLjABAAAA7JftEZyQsA5AnLE8CETTQ17oFzY7fX8nFR2gj5E0icA"
    },
    {
      "rank": 24,
      "accountName": "-叮当猫-",
      "category": "游戏",
      "comprehensiveScore": 60.5,
      "followers": "138.55w",
      "newFans": "46.30w",
      "newLikes": "121.57w",
      "newComments": "55.20w",
      "newShares": "12.87w",
      "profileUrl": "https://www.douyin.com/user/MS4wLjABAAAA8I9Gj30wvDm6w0Eyl5Trom-oOh5tVtHeiMxF4dTKCtZNwY1hB4BlcAN4hWkQkF9U"
    },
    {
      "rank": 25,
      "accountName": "NiuNiuSlime",
      "category": "游戏",
      "comprehensiveScore": 60.3,
      "followers": "202.06w",
      "newFans": "15.51w",
      "newLikes": "130.88w",
      "newComments": "14.72w",
      "newShares": "49.54w",
      "profileUrl": "https://www.douyin.com/user/MS4wLjABAAAAqNhNY6B8UohZLzRQoEyLphC9x4rogENZsgxdX9Y5Av8UZIQlhxewOwmVHx_d3RKW"
    },
    {
      "rank": 26,
      "accountName": "和平精英",
      "category": "游戏",
      "comprehensiveScore": 59.9,
      "followers": "1488.70w",
      "newFans": "6.39w",
      "newLikes": "151.76w",
      "newComments": "5.83w",
      "newShares": "33.18w",
      "profileUrl": "https://www.douyin.com/user/MS4wLjABAAAAUXB3z4cYRG_dwUf7H2-QAF_7RPw3gzVMGqkj99q73Og7tizaEibvuF9VsgERZzGl"
    },
    {
      "rank": 27,
      "accountName": "泽塔来啦",
      "category": "游戏",
      "comprehensiveScore": 59.9,
      "followers": "230.54w",
      "newFans": "138.06w",
      "newLikes": "109.77w",
      "newComments": "13.56w",
      "newShares": "6.45w",
      "profileUrl": "https://www.douyin.com/user/MS4wLjABAAAAsnFY-1dspAB0lEPCORk0sezaUeqFu9PF3XQRUa2MK0I"
    },
    {
      "rank": 28,
      "accountName": "龙🐲",
      "category": "游戏",
      "comprehensiveScore": 59.8,
      "followers": "176.12w",
      "newFans": "87.73w",
      "newLikes": "151.38w",
      "newComments": "22.07w",
      "newShares": "6.80w",
      "profileUrl": "https://www.douyin.com/user/MS4wLjABAAAAl8y38w-goq56evF8FoCg_l91QDWbq6PPw7c1QvzgVCnIP9BbCjr3vONjoVlT44m_"
    },
    {
      "rank": 29,
      "accountName": "麻辣毛蛋儿",
      "category": "游戏",
      "comprehensiveScore": 59.4,
      "followers": "657.56w",
      "newFans": "30.72w",
      "newLikes": "160.58w",
      "newComments": "9.67w",
      "newShares": "9.67w",
      "profileUrl": "https://www.douyin.com/user/MS4wLjABAAAAwHZPIKQuJCoNJnbYbyvCj-rkVdlSAw2mTfZqVGUp8PecZzduk6R4QRarqdwsOMOO"
    },
    {
      "rank": 30,
      "accountName": "Horcus",
      "category": "游戏",
      "comprehensiveScore": 59.2,
      "followers": "306.79w",
      "newFans": "18.03w",
      "newLikes": "372.78w",
      "newComments": "1.46w",
      "newShares": "32.17w",
      "profileUrl": "https://www.douyin.com/user/MS4wLjABAAAAFhy9PPe-pHOCEfiB_vUT1SixbZ1tcoDdyYoDUvJ5femkSv_03G9F-WDAaDRWfx_q"
    },
    {
      "rank": 31,
      "accountName": "火影忍者手游情报君",
      "category": "游戏",
      "comprehensiveScore": 59.1,
      "followers": "336.60w",
      "newFans": "4.80w",
      "newLikes": "182.35w",
      "newComments": "11.68w",
      "newShares": "57.85w",
      "profileUrl": "https://www.douyin.com/user/MS4wLjABAAAANDS_eu7UiTSg90SgpxB9U984KMOp8Qxc85wad9OSUk8"
    },
    {
      "rank": 32,
      "accountName": "小五哥哥『九方骏』",
      "category": "游戏",
      "comprehensiveScore": 59,
      "followers": "1409.08w",
      "newFans": "15.15w",
      "newLikes": "152.97w",
      "newComments": "2.30w",
      "newShares": "19.96w",
      "profileUrl": "https://www.douyin.com/user/MS4wLjABAAAAljwH0ZOASCHirg_nZCW_RWdMbzGISXvu_fa4rbo5vTQ"
    },
    {
      "rank": 33,
      "accountName": "幻术（光明神）",
      "category": "游戏",
      "comprehensiveScore": 59,
      "followers": "315.20w",
      "newFans": "23.17w",
      "newLikes": "240.26w",
      "newComments": "3.81w",
      "newShares": "22.37w",
      "profileUrl": "https://www.douyin.com/user/MS4wLjABAAAARhIJ0nz0kWoQA_w1bYkthnfsykIjtYx8TLJWd6YKVcrmfCgjBj-0lGumAeg-QRc6"
    },
    {
      "rank": 34,
      "accountName": "南瓜（爱玩铠的帅哥）",
      "category": "游戏",
      "comprehensiveScore": 58.7,
      "followers": "185.24w",
      "newFans": "61.42w",
      "newLikes": "252.42w",
      "newComments": "5.08w",
      "newShares": "10.26w",
      "profileUrl": "https://www.douyin.com/user/MS4wLjABAAAAjrW-45_W2O1UIYZYD_khR_cj5-DyU198nD8WwnFTdPA"
    },
    {
      "rank": 35,
      "accountName": "课本君",
      "category": "游戏",
      "comprehensiveScore": 58.6,
      "followers": "257.75w",
      "newFans": "37.49w",
      "newLikes": "149.90w",
      "newComments": "17.09w",
      "newShares": "9.91w",
      "profileUrl": "https://www.douyin.com/user/MS4wLjABAAAAutYbR1772l79rttRaiX4gqqnO7KNnRXTEAIMW2dEmgE"
    },
    {
      "rank": 36,
      "accountName": "大眼东👀",
      "category": "游戏",
      "comprehensiveScore": 58.4,
      "followers": "938.82w",
      "newFans": "11.73w",
      "newLikes": "142.88w",
      "newComments": "2.74w",
      "newShares": "28.27w",
      "profileUrl": "https://www.douyin.com/user/MS4wLjABAAAAUAViiww0hfmFPAsfeOoC-5hieOmtnnIDMbqrLW1MEQQ"
    },
    {
      "rank": 37,
      "accountName": "高司令（速凌电竞）",
      "category": "游戏",
      "comprehensiveScore": 58.3,
      "followers": "596.76w",
      "newFans": "13.17w",
      "newLikes": "228.71w",
      "newComments": "3.23w",
      "newShares": "21.93w",
      "profileUrl": "https://www.douyin.com/user/MS4wLjABAAAAodVA_VV5FRuduX8E4qUoL9sAljeXkV0YdPXh86U0izCnEIXbNnoXYCutvEWsLnju"
    },
    {
      "rank": 38,
      "accountName": "包子（三角洲行动）",
      "category": "游戏",
      "comprehensiveScore": 58.3,
      "followers": "206.57w",
      "newFans": "76.93w",
      "newLikes": "166.96w",
      "newComments": "1.33w",
      "newShares": "17.16w",
      "profileUrl": "https://www.douyin.com/user/MS4wLjABAAAAiD9HH1VL7PueXe2ZyfZbP7i97xp2N5hSpnlVqP7bh0E"
    },
    {
      "rank": 39,
      "accountName": "我是庄小周🐳",
      "category": "游戏",
      "comprehensiveScore": 57.7,
      "followers": "230.58w",
      "newFans": "40.21w",
      "newLikes": "142.17w",
      "newComments": "3.86w",
      "newShares": "18.25w",
      "profileUrl": "https://www.douyin.com/user/MS4wLjABAAAAPicXTPezaLc6WjmJEiFdTwNPk0ZIRaamqcm9rTYffF_QIcw4_EtyD3zn1PAUoJLp"
    },
    {
      "rank": 40,
      "accountName": "AG超玩会一诺",
      "category": "游戏",
      "comprehensiveScore": 57.6,
      "followers": "775.27w",
      "newFans": "11.73w",
      "newLikes": "212.70w",
      "newComments": "6.21w",
      "newShares": "12.69w",
      "profileUrl": "https://www.douyin.com/user/MS4wLjABAAAA0plEjJa_eRXpUhYAKdsacL08pT_kVm0ByvYinE6_pxQHDQblBITv7RYL211NBGZC"
    },
    {
      "rank": 41,
      "accountName": "九尾",
      "category": "游戏",
      "comprehensiveScore": 57.3,
      "followers": "162.01w",
      "newFans": "70.71w",
      "newLikes": "118.81w",
      "newComments": "20.76w",
      "newShares": "5.63w",
      "profileUrl": "https://www.douyin.com/user/MS4wLjABAAAAZeVZjgcgDgr1YE3AAnMbK5N42FJVBobEw2m8q854JkVZG2wVyacNlr3xUUfuJy31"
    },
    {
      "rank": 42,
      "accountName": "可杰",
      "category": "游戏",
      "comprehensiveScore": 56.4,
      "followers": "554.95w",
      "newFans": "19.72w",
      "newLikes": "94.74w",
      "newComments": "2.89w",
      "newShares": "20.31w",
      "profileUrl": "https://www.douyin.com/user/MS4wLjABAAAA8qrPg8x26mCUFqA6_qJ9czybLqKPZlD3JYw_hFWwThs"
    },
    {
      "rank": 43,
      "accountName": "你的影月月(求点赞求推荐OWO)",
      "category": "游戏",
      "comprehensiveScore": 55.1,
      "followers": "370.34w",
      "newFans": "45.05w",
      "newLikes": "69.74w",
      "newComments": "2.94w",
      "newShares": "11.40w",
      "profileUrl": "https://www.douyin.com/user/MS4wLjABAAAAB-GU6vcwfrTcnHCeWUghQCcUyy1Lw8knY1J4qX08elq45SvG_r7-ms25btK69KnP"
    },
    {
      "rank": 44,
      "accountName": "九迁忆姐弟组合",
      "category": "游戏",
      "comprehensiveScore": 54.9,
      "followers": "180.28w",
      "newFans": "34.01w",
      "newLikes": "87.94w",
      "newComments": "10.70w",
      "newShares": "10.39w",
      "profileUrl": "https://www.douyin.com/user/MS4wLjABAAAAlFxbIm4nzWwG8XCsB6vDGRd4nJdfVPmsITqrFFpXSir9vIc1Caa9nTrh6n6HvEm6"
    },
    {
      "rank": 45,
      "accountName": "果果小兔KocoBunny",
      "category": "游戏",
      "comprehensiveScore": 54.4,
      "followers": "446.40w",
      "newFans": "27.53w",
      "newLikes": "84.41w",
      "newComments": "30.60w",
      "newShares": "2.74w",
      "profileUrl": "https://www.douyin.com/user/MS4wLjABAAAAAuzG_fjZzVAUbQmzS6L4c82TdPfnDSVno0xnTEPNemk"
    },
    {
      "rank": 46,
      "accountName": "小黄蜂游戏主播",
      "category": "游戏",
      "comprehensiveScore": 54,
      "followers": "469.51w",
      "newFans": "24.56w",
      "newLikes": "77.16w",
      "newComments": "7.22w",
      "newShares": "7.22w",
      "profileUrl": "https://www.douyin.com/user/MS4wLjABAAAA1b2bRAaMFD_kPHLoZnQFc81SpHxRGbrtyyFQjqL-G9tQ0TqxEGdtzX2EN1n_M6bQ"
    },
    {
      "rank": 47,
      "accountName": "苏醒（三角洲行动）",
      "category": "游戏",
      "comprehensiveScore": 53.4,
      "followers": "401.97w",
      "newFans": "25.79w",
      "newLikes": "164.77w",
      "newComments": "1.88w",
      "newShares": "6.64w",
      "profileUrl": "https://www.douyin.com/user/MS4wLjABAAAAaqJBNnYgc6qJkgTGAN68vTM2uXCunwc7tKyVNA-VauU"
    },
    {
      "rank": 48,
      "accountName": "暗区突围",
      "category": "游戏",
      "comprehensiveScore": 53.3,
      "followers": "407.23w",
      "newFans": "3.61w",
      "newLikes": "90.01w",
      "newComments": "9.40w",
      "newShares": "26.79w",
      "profileUrl": "https://www.douyin.com/user/MS4wLjABAAAAjMZE28DKEtogahS2jrtUkirxL4myrZ34AT9qWJ7cYtXPrYQQqIOG8WZ2lNGlAQG2"
    },
    {
      "rank": 49,
      "accountName": "江鸽北主任",
      "category": "游戏",
      "comprehensiveScore": 52.9,
      "followers": "765.12w",
      "newFans": "3.56w",
      "newLikes": "150.24w",
      "newComments": "1.57w",
      "newShares": "23.55w",
      "profileUrl": "https://www.douyin.com/user/MS4wLjABAAAAABHPycvUAAR44hXwj3YCkLT7_-ON2vONwUncb9yh3ErQd4J2HOBEJk0wR8-xB47b"
    },
    {
      "rank": 50,
      "accountName": "游小浪Game",
      "category": "游戏",
      "comprehensiveScore": 49.1,
      "followers": "1112.65w",
      "newFans": "7.83w",
      "newLikes": "53.82w",
      "newComments": "6.21w",
      "newShares": "3.76w",
      "profileUrl": "https://www.douyin.com/user/MS4wLjABAAAAddAVNREsUtLPk1BGCE53tqnPxMslAnDZMPS4lnLWWYA"
    }
  ]
}